[{"deal_date":"2016-08-12","floor":"2","deal_amount":"42240"},{"deal_date":"2016-08-12","floor":"11","deal_amount":"46602"},{"deal_date":"2016-08-12","floor":"2","deal_amount":"42240"},{"deal_date":"2016-08-12","floor":"11","deal_amount":"46602"},{"deal_date":"2016-08-18","floor":"15","deal_amount":"46102"},{"deal_date":"2016-08-18","floor":"15","deal_amount":"46102"},{"deal_date":"2016-08-22","floor":"15","deal_amount":"46102"},{"deal_date":"2016-08-22","floor":"15","deal_amount":"46102"},{"deal_date":"2016-08-22","floor":"15","deal_amount":"46102"},{"deal_date":"2016-08-22","floor":"15","deal_amount":"46102"},{"deal_date":"2016-08-23","floor":"10","deal_amount":"46652"},{"deal_date":"2016-08-23","floor":"10","deal_amount":"46652"},{"deal_date":"2016-08-29","floor":"2","deal_amount":"42540"},{"deal_date":"2016-08-29","floor":"2","deal_amount":"42540"},{"deal_date":"2016-09-03","floor":"14","deal_amount":"46102"},{"deal_date":"2016-09-03","floor":"14","deal_amount":"46102"},{"deal_date":"2016-09-07","floor":"12","deal_amount":"46102"},{"deal_date":"2016-09-07","floor":"12","deal_amount":"46102"},{"deal_date":"2016-09-10","floor":"1","deal_amount":"42200"},{"deal_date":"2016-09-10","floor":"1","deal_amount":"42200"},{"deal_date":"2016-09-12","floor":"17","deal_amount":"46102"},{"deal_date":"2016-09-12","floor":"17","deal_amount":"46102"},{"deal_date":"2016-09-26","floor":"5","deal_amount":"46102"},{"deal_date":"2016-09-26","floor":"7","deal_amount":"45602"},{"deal_date":"2016-09-26","floor":"5","deal_amount":"46102"},{"deal_date":"2016-09-26","floor":"7","deal_amount":"45602"},{"deal_date":"2016-10-10","floor":"12","deal_amount":"46602"},{"deal_date":"2016-10-10","floor":"12","deal_amount":"46602"},{"deal_date":"2016-10-13","floor":"13","deal_amount":"46602"},{"deal_date":"2016-10-13","floor":"13","deal_amount":"46602"},{"deal_date":"2016-11-08","floor":"10","deal_amount":"46602"},{"deal_date":"2016-11-08","floor":"10","deal_amount":"46602"},{"deal_date":"2017-02-04","floor":"16","deal_amount":"48012"},{"deal_date":"2017-02-04","floor":"16","deal_amount":"48012"},{"deal_date":"2017-06-07","floor":"10","deal_amount":"46652"},{"deal_date":"2017-06-07","floor":"10","deal_amount":"46652"},{"deal_date":"2017-06-08","floor":"12","deal_amount":"47102"},{"deal_date":"2017-06-08","floor":"12","deal_amount":"47102"},{"deal_date":"2017-06-28","floor":"11","deal_amount":"48910"},{"deal_date":"2017-06-28","floor":"11","deal_amount":"48910"}]