[{"cate_cd":"101123125101105","cate1_nm":"서울특별시","cate2_nm":"종로구","cate3_nm":null,"dong":" 익선동","apt":"운현신화타워","build_year":"1998","deal_date":"20060109","floor":"12","deal_amount":"15741"},{"cate_cd":"101123125101105","cate1_nm":"서울특별시","cate2_nm":"종로구","cate3_nm":null,"dong":" 익선동","apt":"운현신화타워","build_year":"1998","deal_date":"20110112","floor":"9","deal_amount":"32000"},{"cate_cd":"101123125101105","cate1_nm":"서울특별시","cate2_nm":"종로구","cate3_nm":null,"dong":" 익선동","apt":"운현신화타워","build_year":"1998","deal_date":"20140314","floor":"7","deal_amount":"26000"},{"cate_cd":"101123125101105","cate1_nm":"서울특별시","cate2_nm":"종로구","cate3_nm":null,"dong":" 익선동","apt":"운현신화타워","build_year":"1998","deal_date":"20140606","floor":"6","deal_amount":"28500"},{"cate_cd":"101123125101105","cate1_nm":"서울특별시","cate2_nm":"종로구","cate3_nm":null,"dong":" 익선동","apt":"운현신화타워","build_year":"1998","deal_date":"20141218","floor":"13","deal_amount":"31000"},{"cate_cd":"101123125101105","cate1_nm":"서울특별시","cate2_nm":"종로구","cate3_nm":null,"dong":" 익선동","apt":"운현신화타워","build_year":"1998","deal_date":"20150410","floor":"11","deal_amount":"30900"},{"cate_cd":"101123125101105","cate1_nm":"서울특별시","cate2_nm":"종로구","cate3_nm":null,"dong":" 익선동","apt":"운현신화타워","build_year":"1998","deal_date":"20180501","floor":"7","deal_amount":"32700"}]