[{"cate_cd":"102116104167101","cate1_nm":"부산광역시","cate2_nm":"해운대구","cate3_nm":null,"dong":" 우동","apt":"해운대센텀 미진이지비아 아파트","build_year":"2020","deal_date":"20200617","floor":"10","deal_amount":"55710"},{"cate_cd":"102116104167101","cate1_nm":"부산광역시","cate2_nm":"해운대구","cate3_nm":null,"dong":" 우동","apt":"해운대센텀 미진이지비아 아파트","build_year":"2020","deal_date":"20200617","floor":"10","deal_amount":"55710"},{"cate_cd":"102116104167101","cate1_nm":"부산광역시","cate2_nm":"해운대구","cate3_nm":null,"dong":" 우동","apt":"해운대센텀 미진이지비아 아파트","build_year":"2020","deal_date":"20200618","floor":"25","deal_amount":"63840"},{"cate_cd":"102116104167101","cate1_nm":"부산광역시","cate2_nm":"해운대구","cate3_nm":null,"dong":" 우동","apt":"해운대센텀 미진이지비아 아파트","build_year":"2020","deal_date":"20200618","floor":"25","deal_amount":"63840"},{"cate_cd":"102116104167101","cate1_nm":"부산광역시","cate2_nm":"해운대구","cate3_nm":null,"dong":" 우동","apt":"해운대센텀 미진이지비아 아파트","build_year":"2020","deal_date":"20200626","floor":"8","deal_amount":"55710"},{"cate_cd":"102116104167101","cate1_nm":"부산광역시","cate2_nm":"해운대구","cate3_nm":null,"dong":" 우동","apt":"해운대센텀 미진이지비아 아파트","build_year":"2020","deal_date":"20200626","floor":"8","deal_amount":"55710"},{"cate_cd":"102116104167101","cate1_nm":"부산광역시","cate2_nm":"해운대구","cate3_nm":null,"dong":" 우동","apt":"해운대센텀 미진이지비아 아파트","build_year":"2020","deal_date":"20200627","floor":"19","deal_amount":"59650"},{"cate_cd":"102116104167101","cate1_nm":"부산광역시","cate2_nm":"해운대구","cate3_nm":null,"dong":" 우동","apt":"해운대센텀 미진이지비아 아파트","build_year":"2020","deal_date":"20200627","floor":"19","deal_amount":"59650"},{"cate_cd":"102116104167101","cate1_nm":"부산광역시","cate2_nm":"해운대구","cate3_nm":null,"dong":" 우동","apt":"해운대센텀 미진이지비아 아파트","build_year":"2020","deal_date":"20200629","floor":"14","deal_amount":"57100"},{"cate_cd":"102116104167101","cate1_nm":"부산광역시","cate2_nm":"해운대구","cate3_nm":null,"dong":" 우동","apt":"해운대센텀 미진이지비아 아파트","build_year":"2020","deal_date":"20200629","floor":"14","deal_amount":"57100"},{"cate_cd":"102116104167101","cate1_nm":"부산광역시","cate2_nm":"해운대구","cate3_nm":null,"dong":" 우동","apt":"해운대센텀 미진이지비아 아파트","build_year":"2020","deal_date":"20200630","floor":"22","deal_amount":"62780"},{"cate_cd":"102116104167101","cate1_nm":"부산광역시","cate2_nm":"해운대구","cate3_nm":null,"dong":" 우동","apt":"해운대센텀 미진이지비아 아파트","build_year":"2020","deal_date":"20200630","floor":"22","deal_amount":"62780"},{"cate_cd":"102116104167101","cate1_nm":"부산광역시","cate2_nm":"해운대구","cate3_nm":null,"dong":" 우동","apt":"해운대센텀 미진이지비아 아파트","build_year":"2020","deal_date":"20200709","floor":"21","deal_amount":"61980"},{"cate_cd":"102116104167101","cate1_nm":"부산광역시","cate2_nm":"해운대구","cate3_nm":null,"dong":" 우동","apt":"해운대센텀 미진이지비아 아파트","build_year":"2020","deal_date":"20200709","floor":"21","deal_amount":"61980"},{"cate_cd":"102116104167101","cate1_nm":"부산광역시","cate2_nm":"해운대구","cate3_nm":null,"dong":" 우동","apt":"해운대센텀 미진이지비아 아파트","build_year":"2020","deal_date":"20200720","floor":"28","deal_amount":"65720"},{"cate_cd":"102116104167101","cate1_nm":"부산광역시","cate2_nm":"해운대구","cate3_nm":null,"dong":" 우동","apt":"해운대센텀 미진이지비아 아파트","build_year":"2020","deal_date":"20200720","floor":"28","deal_amount":"65720"},{"cate_cd":"102116104167101","cate1_nm":"부산광역시","cate2_nm":"해운대구","cate3_nm":null,"dong":" 우동","apt":"해운대센텀 미진이지비아 아파트","build_year":"2020","deal_date":"20200828","floor":"22","deal_amount":"63980"},{"cate_cd":"102116104167101","cate1_nm":"부산광역시","cate2_nm":"해운대구","cate3_nm":null,"dong":" 우동","apt":"해운대센텀 미진이지비아 아파트","build_year":"2020","deal_date":"20200828","floor":"22","deal_amount":"63980"},{"cate_cd":"102116104167101","cate1_nm":"부산광역시","cate2_nm":"해운대구","cate3_nm":null,"dong":" 우동","apt":"해운대센텀 미진이지비아 아파트","build_year":"2020","deal_date":"20200923","floor":"22","deal_amount":"65000"},{"cate_cd":"102116104167101","cate1_nm":"부산광역시","cate2_nm":"해운대구","cate3_nm":null,"dong":" 우동","apt":"해운대센텀 미진이지비아 아파트","build_year":"2020","deal_date":"20200923","floor":"22","deal_amount":"65000"},{"cate_cd":"102116104167101","cate1_nm":"부산광역시","cate2_nm":"해운대구","cate3_nm":null,"dong":" 우동","apt":"해운대센텀 미진이지비아 아파트","build_year":"2020","deal_date":"20200929","floor":"16","deal_amount":"59750"},{"cate_cd":"102116104167101","cate1_nm":"부산광역시","cate2_nm":"해운대구","cate3_nm":null,"dong":" 우동","apt":"해운대센텀 미진이지비아 아파트","build_year":"2020","deal_date":"20200929","floor":"16","deal_amount":"59750"},{"cate_cd":"102116104167101","cate1_nm":"부산광역시","cate2_nm":"해운대구","cate3_nm":null,"dong":" 우동","apt":"해운대센텀 미진이지비아 아파트","build_year":"2020","deal_date":"20201114","floor":"24","deal_amount":"85000"},{"cate_cd":"102116104167101","cate1_nm":"부산광역시","cate2_nm":"해운대구","cate3_nm":null,"dong":" 우동","apt":"해운대센텀 미진이지비아 아파트","build_year":"2020","deal_date":"20201114","floor":"24","deal_amount":"85000"}]