[{"cate_cd":"104107119107105","cate1_nm":"인천광역시","cate2_nm":"서구","cate3_nm":null,"dong":"가정동","apt":"루원더퍼스트","build_year":"2019","deal_date":"2019-12-30","floor":"11","deal_amount":"36399"},{"cate_cd":"104107119107105","cate1_nm":"인천광역시","cate2_nm":"서구","cate3_nm":null,"dong":"가정동","apt":"루원더퍼스트","build_year":"2019","deal_date":"2020-06-14","floor":"2","deal_amount":"43300"},{"cate_cd":"104107119107105","cate1_nm":"인천광역시","cate2_nm":"서구","cate3_nm":null,"dong":"가정동","apt":"루원더퍼스트","build_year":"2019","deal_date":"2021-06-02","floor":"12","deal_amount":"59300"}]