[{"cate_cd":"106104114158106","cate1_nm":"대전광역시","cate2_nm":"유성구","cate3_nm":null,"dong":" 봉명동","apt":"좋은하루3차","build_year":"2013","deal_date":"20130611","floor":"12","deal_amount":"6850"},{"cate_cd":"106104114158106","cate1_nm":"대전광역시","cate2_nm":"유성구","cate3_nm":null,"dong":" 봉명동","apt":"좋은하루3차","build_year":"2013","deal_date":"20130720","floor":"11","deal_amount":"6850"},{"cate_cd":"106104114158106","cate1_nm":"대전광역시","cate2_nm":"유성구","cate3_nm":null,"dong":" 봉명동","apt":"좋은하루3차","build_year":"2013","deal_date":"20131029","floor":"8","deal_amount":"6700"},{"cate_cd":"106104114158106","cate1_nm":"대전광역시","cate2_nm":"유성구","cate3_nm":null,"dong":" 봉명동","apt":"좋은하루3차","build_year":"2013","deal_date":"20131101","floor":"9","deal_amount":"6850"},{"cate_cd":"106104114158106","cate1_nm":"대전광역시","cate2_nm":"유성구","cate3_nm":null,"dong":" 봉명동","apt":"좋은하루3차","build_year":"2013","deal_date":"20131107","floor":"7","deal_amount":"5975"},{"cate_cd":"106104114158106","cate1_nm":"대전광역시","cate2_nm":"유성구","cate3_nm":null,"dong":" 봉명동","apt":"좋은하루3차","build_year":"2013","deal_date":"20131107","floor":"6","deal_amount":"5975"},{"cate_cd":"106104114158106","cate1_nm":"대전광역시","cate2_nm":"유성구","cate3_nm":null,"dong":" 봉명동","apt":"좋은하루3차","build_year":"2013","deal_date":"20161108","floor":"9","deal_amount":"6500"}]