[{"cate_cd":"107101101143101","cate1_nm":"울산광역시","cate2_nm":"남구","cate3_nm":null,"dong":" 달동","apt":"울산센트럴자이","build_year":"2015","deal_date":"2017-01-03","floor":"22","deal_amount":"63000"},{"cate_cd":"107101101143101","cate1_nm":"울산광역시","cate2_nm":"남구","cate3_nm":null,"dong":" 달동","apt":"울산센트럴자이","build_year":"2015","deal_date":"2018-01-23","floor":"11","deal_amount":"59800"},{"cate_cd":"107101101143101","cate1_nm":"울산광역시","cate2_nm":"남구","cate3_nm":null,"dong":" 달동","apt":"울산센트럴자이","build_year":"2015","deal_date":"2020-01-20","floor":"24","deal_amount":"57000"},{"cate_cd":"107101101143101","cate1_nm":"울산광역시","cate2_nm":"남구","cate3_nm":null,"dong":" 달동","apt":"울산센트럴자이","build_year":"2015","deal_date":"2020-02-04","floor":"16","deal_amount":"49000"},{"cate_cd":"107101101143101","cate1_nm":"울산광역시","cate2_nm":"남구","cate3_nm":null,"dong":" 달동","apt":"울산센트럴자이","build_year":"2015","deal_date":"2020-07-03","floor":"14","deal_amount":"57500"},{"cate_cd":"107101101143101","cate1_nm":"울산광역시","cate2_nm":"남구","cate3_nm":null,"dong":" 달동","apt":"울산센트럴자이","build_year":"2015","deal_date":"2020-08-20","floor":"7","deal_amount":"52800"},{"cate_cd":"107101101143101","cate1_nm":"울산광역시","cate2_nm":"남구","cate3_nm":null,"dong":" 달동","apt":"울산센트럴자이","build_year":"2015","deal_date":"2020-09-14","floor":"8","deal_amount":"57500"},{"cate_cd":"107101101143101","cate1_nm":"울산광역시","cate2_nm":"남구","cate3_nm":null,"dong":" 달동","apt":"울산센트럴자이","build_year":"2015","deal_date":"2020-10-10","floor":"11","deal_amount":"60500"},{"cate_cd":"107101101143101","cate1_nm":"울산광역시","cate2_nm":"남구","cate3_nm":null,"dong":" 달동","apt":"울산센트럴자이","build_year":"2015","deal_date":"2020-10-13","floor":"14","deal_amount":"58500"},{"cate_cd":"107101101143101","cate1_nm":"울산광역시","cate2_nm":"남구","cate3_nm":null,"dong":" 달동","apt":"울산센트럴자이","build_year":"2015","deal_date":"2020-10-14","floor":"5","deal_amount":"58000"},{"cate_cd":"107101101143101","cate1_nm":"울산광역시","cate2_nm":"남구","cate3_nm":null,"dong":" 달동","apt":"울산센트럴자이","build_year":"2015","deal_date":"2020-10-15","floor":"24","deal_amount":"62000"},{"cate_cd":"107101101143101","cate1_nm":"울산광역시","cate2_nm":"남구","cate3_nm":null,"dong":" 달동","apt":"울산센트럴자이","build_year":"2015","deal_date":"2020-10-26","floor":"6","deal_amount":"59500"},{"cate_cd":"107101101143101","cate1_nm":"울산광역시","cate2_nm":"남구","cate3_nm":null,"dong":" 달동","apt":"울산센트럴자이","build_year":"2015","deal_date":"2020-10-31","floor":"7","deal_amount":"57200"},{"cate_cd":"107101101143101","cate1_nm":"울산광역시","cate2_nm":"남구","cate3_nm":null,"dong":" 달동","apt":"울산센트럴자이","build_year":"2015","deal_date":"2020-11-09","floor":"20","deal_amount":"62000"},{"cate_cd":"107101101143101","cate1_nm":"울산광역시","cate2_nm":"남구","cate3_nm":null,"dong":" 달동","apt":"울산센트럴자이","build_year":"2015","deal_date":"2020-11-14","floor":"29","deal_amount":"69000"},{"cate_cd":"107101101143101","cate1_nm":"울산광역시","cate2_nm":"남구","cate3_nm":null,"dong":" 달동","apt":"울산센트럴자이","build_year":"2015","deal_date":"2020-11-19","floor":"13","deal_amount":"67000"}]