[{"cate_cd":"109128119112101","cate1_nm":"경기도","cate2_nm":"평택시","cate3_nm":null,"dong":" 평택동","apt":"어반스페이스(UrbanSpace)","build_year":"2018","deal_date":"2018-06-26","floor":"7","deal_amount":"12300"},{"cate_cd":"109128119112101","cate1_nm":"경기도","cate2_nm":"평택시","cate3_nm":null,"dong":" 평택동","apt":"어반스페이스(UrbanSpace)","build_year":"2018","deal_date":"2018-07-02","floor":"9","deal_amount":"12500"},{"cate_cd":"109128119112101","cate1_nm":"경기도","cate2_nm":"평택시","cate3_nm":null,"dong":" 평택동","apt":"어반스페이스(UrbanSpace)","build_year":"2018","deal_date":"2018-08-31","floor":"8","deal_amount":"12500"},{"cate_cd":"109128119112101","cate1_nm":"경기도","cate2_nm":"평택시","cate3_nm":null,"dong":" 평택동","apt":"어반스페이스(UrbanSpace)","build_year":"2018","deal_date":"2019-02-14","floor":"5","deal_amount":"12000"},{"cate_cd":"109128119112101","cate1_nm":"경기도","cate2_nm":"평택시","cate3_nm":null,"dong":" 평택동","apt":"어반스페이스(UrbanSpace)","build_year":"2018","deal_date":"2019-02-14","floor":"5","deal_amount":"12000"},{"cate_cd":"109128119112101","cate1_nm":"경기도","cate2_nm":"평택시","cate3_nm":null,"dong":" 평택동","apt":"어반스페이스(UrbanSpace)","build_year":"2018","deal_date":"2019-06-03","floor":"5","deal_amount":"12000"},{"cate_cd":"109128119112101","cate1_nm":"경기도","cate2_nm":"평택시","cate3_nm":null,"dong":" 평택동","apt":"어반스페이스(UrbanSpace)","build_year":"2018","deal_date":"2019-06-03","floor":"5","deal_amount":"12000"}]